qastudio_pytest/__init__.py
qastudio_pytest/api_client.py
qastudio_pytest/models.py
qastudio_pytest/plugin.py
qastudio_pytest/utils.py
qastudio_pytest-1.0.6.dist-info/licenses/LICENSE
qastudio_pytest-1.0.6.dist-info/METADATA
qastudio_pytest-1.0.6.dist-info/WHEEL
qastudio_pytest-1.0.6.dist-info/entry_points.txt
qastudio_pytest-1.0.6.dist-info/top_level.txt
qastudio_pytest-1.0.6.dist-info/RECORD
