Metadata-Version: 2.4
Name: qastudio-pytest
Version: 1.0.6
Summary: pytest plugin for QAStudio.dev test management platform
Author-email: QAStudio <ben@qastudio.dev>
License: AGPL-3.0-or-later
Project-URL: Homepage, https://github.com/QAStudio-Dev/playwright-reporter-python
Project-URL: Repository, https://github.com/QAStudio-Dev/playwright-reporter-python
Project-URL: Issues, https://github.com/QAStudio-Dev/playwright-reporter-python/issues
Project-URL: Documentation, https://github.com/QAStudio-Dev/playwright-reporter-python#readme
Keywords: pytest,testing,test-management,qa,qastudio
Classifier: Development Status :: 4 - Beta
Classifier: Framework :: Pytest
Classifier: Intended Audience :: Developers
Classifier: License :: OSI Approved :: GNU Affero General Public License v3 or later (AGPLv3+)
Classifier: Operating System :: OS Independent
Classifier: Programming Language :: Python :: 3
Classifier: Programming Language :: Python :: 3.8
Classifier: Programming Language :: Python :: 3.9
Classifier: Programming Language :: Python :: 3.10
Classifier: Programming Language :: Python :: 3.11
Classifier: Programming Language :: Python :: 3.12
Classifier: Topic :: Software Development :: Testing
Requires-Python: >=3.8
License-File: LICENSE
Requires-Dist: pytest>=7.0.0
Requires-Dist: requests>=2.28.0
Provides-Extra: dev
Requires-Dist: pytest>=7.0.0; extra == "dev"
Requires-Dist: pytest-cov>=4.0.0; extra == "dev"
Requires-Dist: black>=23.0.0; extra == "dev"
Requires-Dist: flake8>=6.0.0; extra == "dev"
Requires-Dist: mypy>=1.0.0; extra == "dev"
Requires-Dist: types-requests>=2.28.0; extra == "dev"
Dynamic: license-file
